{
  "UID": null,
  "ArgumentType": "domain",
  "Command": "dmarc",
  "IsTransitioned": false,
  "CommandArgument": "joomla.org",
  "TimeRecorded": "2025-03-11T06:54:51.6622201-05:00",
  "ReportingNameServer": "maisie.ns.cloudflare.com",
  "TimeToComplete": "115",
  "RelatedIP": null,
  "ResourceRecordType": 16,
  "IsEmptySubDomain": false,
  "SPF_Subaction_Detail": {
    "Void_lookups": null,
    "Invalid_Redirects": null,
    "Recursive_Paths": null,
    "Invalid_Includes": null,
    "Deprecated_SPF_Records": null,
    "MX_Resource_Records": null,
    "Modifier_Ignored": null,
    "Included_Lookups": null,
    "Duplicate_Includes": null
  },
  "Records": [
    "v=DMARC1; p=quarantine; rua=mailto:joomla-t@dmarc.report-uri.com;"
  ],
  "IsEndpoint": false,
  "HasSubscriptions": false,
  "AlertgroupSubscriptionId": null,
  "Failed": [],
  "Warnings": [],
  "Passed": [
    {
      "ID": 441,
      "Name": "DMARC Record Published",
      "Info": "DMARC Record found",
      "Url": "https://mxtoolbox.com/Problem/dmarc/DMARC-Record-Published?page=prob_dmarc&showlogin=1&hidetoc=1&action=dmarc:joomla.org",
      "PublicDescription": null,
      "IsExcludedByUser": false
    },
    {
      "ID": 463,
      "Name": "DMARC Syntax Check",
      "Info": "The record is valid",
      "Url": "https://mxtoolbox.com/Problem/dmarc/DMARC-Syntax-Check?page=prob_dmarc&showlogin=1&hidetoc=1&action=dmarc:joomla.org",
      "PublicDescription": null,
      "IsExcludedByUser": false
    },
    {
      "ID": 504,
      "Name": "DMARC External Validation",
      "Info": "All external domains in your DMARC record are giving permission to send them DMARC reports.",
      "Url": "https://mxtoolbox.com/Problem/dmarc/DMARC-External-Validation?page=prob_dmarc&showlogin=1&hidetoc=1&action=dmarc:joomla.org",
      "PublicDescription": null,
      "IsExcludedByUser": false
    },
    {
      "ID": 505,
      "Name": "DMARC Multiple Records",
      "Info": "Multiple DMARC records corrected to a single record.",
      "Url": "https://mxtoolbox.com/Problem/dmarc/DMARC-Multiple-Records?page=prob_dmarc&showlogin=1&hidetoc=1&action=dmarc:joomla.org",
      "PublicDescription": null,
      "IsExcludedByUser": false
    },
    {
      "ID": 197,
      "Name": "DMARC Policy Not Enabled",
      "Info": "DMARC Quarantine/Reject policy enabled",
      "Url": "https://mxtoolbox.com/Problem/dmarc/DMARC-Policy-Not-Enabled?page=prob_dmarc&showlogin=1&hidetoc=1&action=dmarc:joomla.org",
      "PublicDescription": null,
      "IsExcludedByUser": false
    }
  ],
  "Timeouts": [],
  "Errors": [],
  "IsError": false,
  "Information": [
    {
      "Tag": "",
      "TagValue": "",
      "Name": "record",
      "Description": "v=DMARC1; p=quarantine; rua=mailto:joomla-t@dmarc.report-uri.com;"
    },
    {
      "Tag": "v",
      "TagValue": "DMARC1",
      "Name": "Version",
      "Description": "Identifies the record retrieved as a DMARC record. It must be the first tag in the list."
    },
    {
      "Tag": "p",
      "TagValue": "quarantine",
      "Name": "Policy",
      "Description": "Policy to apply to email that fails the DMARC test. Valid values can be &#39;none&#39;, &#39;quarantine&#39;, or &#39;reject&#39;."
    },
    {
      "Tag": "rua",
      "TagValue": "mailto:joomla-t@dmarc.report-uri.com",
      "Name": "Receivers",
      "Description": "Addresses to which aggregate feedback is to be sent. Comma separated plain-text list of DMARC URIs."
    }
  ],
  "MultiInformation": [],
  "Transcript": [
    {
      "Transcript": "- - - dmarc:_dmarc.joomla.org\r\n\r\n&emsp; 1 c0.org.afilias-nst.info 199.19.53.1 NON-AUTH 30 ms Received 2 Referrals , rcode=NO_ERROR &emsp; joomla.org.\t3600\tIN\tNS\tcory.ns.cloudflare.com,joomla.org.\t3600\tIN\tNS\tmaisie.ns.cloudflare.com,\r\n&emsp; 2 maisie.ns.cloudflare.com 108.162.194.89 AUTH 0 ms Received 1 Answers , rcode=NO_ERROR &emsp; _dmarc.joomla.org.\t300\tIN\tTXT\tv=DMARC1; p=quarantine; rua=mailto:joomla-t@dmarc.report-uri.com;,\r\nRecord returned is an RFC 7489 TXT record.<br/>\r\nLookupServer 115ms\r\n"
    }
  ],
  "MxRep": 0,
  "EmailServiceProvider": null,
  "DnsServiceProvider": "Cloudflare",
  "DnsServiceProviderIdentifier": "cloudflare.com",
  "RelatedLookups": [
    {
      "Name": "dns lookup",
      "URL": "https://mxtoolbox.com/api/v1/lookup/a/joomla.org",
      "Command": "a",
      "CommandArgument": "joomla.org"
    },
    {
      "Name": "dns check",
      "URL": "https://mxtoolbox.com/api/v1/lookup/dns/joomla.org",
      "Command": "dns",
      "CommandArgument": "joomla.org"
    },
    {
      "Name": "mx lookup",
      "URL": "https://mxtoolbox.com/api/v1/lookup/mx/joomla.org",
      "Command": "mx",
      "CommandArgument": "joomla.org"
    },
    {
      "Name": "spf lookup",
      "URL": "https://mxtoolbox.com/api/v1/lookup/spf/joomla.org",
      "Command": "spf",
      "CommandArgument": "joomla.org"
    },
    {
      "Name": "dns propagation",
      "URL": "https://mxtoolbox.com/api/v1/lookup/dmarc/joomla.org:all",
      "Command": "dmarc",
      "CommandArgument": "joomla.org:all"
    }
  ]
}